mleslab/__init__.py
mleslab/program_logic.py
mleslab/programs/program1.txt
mleslab/programs/program2.txt
mleslab/programs/program3.1.txt
mleslab/programs/program3.2.txt
mleslab/programs/program4.txt
mleslab/programs/program5.txt
mleslab/programs/program6.txt
mleslab/programs/program7.txt
mleslab-1.2.3.dist-info/METADATA
mleslab-1.2.3.dist-info/WHEEL
mleslab-1.2.3.dist-info/top_level.txt
mleslab-1.2.3.dist-info/RECORD
